[1,["4aBvsFrfhPJoeHfu1SE+0H@f9941","feGvn2m0VMnqCcgD06H0zR@f9941","0eMiPlCkpBYrriStKCHi88","22nZEuNs1DzYk6GuWTuS11@6c48a","2b0S8UoptP7Ka4p9lrnOjv@6c48a","4aBvsFrfhPJoeHfu1SE+0H@6c48a","22nZEuNs1DzYk6GuWTuS11@f9941","2b0S8UoptP7Ka4p9lrnOjv@f9941","988mXh/jNHoaSfJsmfKIQo@f9941","988mXh/jNHoaSfJsmfKIQo@6c48a","feGvn2m0VMnqCcgD06H0zR@6c48a"],["node","_textureSource","_spriteFrame","_normalSprite","_font","root","addCoin","level","sound","coinNum","clicktip","startPanel","data"],["cc.SpriteFrame",["cc.Node",["_name","_layer","_components","_prefab","_parent","_children","_lpos"],1,9,4,1,2,5],["cc.Widget",["_alignFlags","_originalHeight","_top","_originalWidth","_left","_bottom","node","__prefab"],-3,1,4],["cc.Sprite",["_sizeMode","node","__prefab","_spriteFrame"],2,1,4,6],["cc.Button",["node","__prefab","_normalSprite"],3,1,4,6],["cc.Label",["_string","_actualFontSize","_isSystemFontUsed","_fontSize","_lineHeight","_spacingX","node","__prefab"],-3,1,4],["cc.Prefab",["_name"],2],["cc.Node",["_name","_layer","_parent","_components","_prefab","_lpos"],1,1,12,4,5],["cc.UITransform",["node","__prefab","_contentSize"],3,1,4,5],["cc.CompPrefabInfo",["fileId"],2],["c0219dt/1RG5q8i+3F0o5Hj",["node","__prefab","startPanel","clicktip","coinNum","sound","level","addCoin"],3,1,4,1,1,1,1,1,1],["cc.PrefabInfo",["fileId","instance","targetOverrides","nestedPrefabInstanceRoots","root","asset"],-1,1,1]],[[9,0,2],[8,0,1,2,1],[11,0,1,2,3,4,5,5],[3,1,2,3,1],[1,0,1,4,2,3,6,3],[7,0,1,2,3,4,5,3],[2,0,3,1,6,7,4],[4,0,1,2,1],[6,0,2],[1,0,1,5,2,3,3],[1,0,1,4,5,2,3,6,3],[1,0,1,4,5,2,3,3],[1,0,1,4,2,3,3],[3,0,1,2,2],[2,0,4,2,6,7,4],[2,0,2,5,1,6,7,5],[10,0,1,2,3,4,5,6,7,1],[4,0,1,1],[5,0,1,2,6,7,4],[5,0,1,3,4,2,5,6,7,7]],[[[{"name":"点击屏幕开始游戏","rect":{"x":0,"y":0,"width":450,"height":63},"offset":{"x":0,"y":0},"originalSize":{"width":450,"height":63},"rotated":false,"capInsets":[0,0,0,0],"vertices":{"rawPosition":[-225,-31.5,0,225,-31.5,0,-225,31.5,0,225,31.5,0],"indexes":[0,1,2,2,1,3],"uv":[0,63,450,63,0,0,450,0],"nuv":[0,0,1,0,0,1,1,1],"minPos":{"x":-225,"y":-31.5,"z":0},"maxPos":{"x":225,"y":31.5,"z":0}},"packable":true,"pixelsToUnit":100,"pivot":{"x":0.5,"y":0.5},"meshType":0}],[0],0,[0],[1],[3]],[[{"name":"金币","rect":{"x":0,"y":0,"width":70,"height":63},"offset":{"x":0,"y":0},"originalSize":{"width":70,"height":63},"rotated":false,"capInsets":[0,0,0,0],"vertices":{"rawPosition":[-35,-31.5,0,35,-31.5,0,-35,31.5,0,35,31.5,0],"indexes":[0,1,2,2,1,3],"uv":[0,63,70,63,0,0,70,0],"nuv":[0,0,1,0,0,1,1,1],"minPos":{"x":-35,"y":-31.5,"z":0},"maxPos":{"x":35,"y":31.5,"z":0}},"packable":true,"pixelsToUnit":100,"pivot":{"x":0.5,"y":0.5},"meshType":0}],[0],0,[0],[1],[4]],[[{"name":"+","rect":{"x":0,"y":0,"width":62,"height":62},"offset":{"x":0,"y":0},"originalSize":{"width":62,"height":62},"rotated":false,"capInsets":[0,0,0,0],"vertices":{"rawPosition":[-31,-31,0,31,-31,0,-31,31,0,31,31,0],"indexes":[0,1,2,2,1,3],"uv":[0,62,62,62,0,0,62,0],"nuv":[0,0,1,0,0,1,1,1],"minPos":{"x":-31,"y":-31,"z":0},"maxPos":{"x":31,"y":31,"z":0}},"packable":true,"pixelsToUnit":100,"pivot":{"x":0.5,"y":0.5},"meshType":0}],[0],0,[0],[1],[5]],[[[8,"UImain"],[9,"UImain",33554432,[-12,-13,-14],[[1,-2,[0,"843K7NqKRFnaqeHZSBw1pv"],[5,750,1440]],[13,0,-3,[0,"07RiSd9sdC4o0hpesWQ53l"]],[6,45,40,36,-4,[0,"5dmOCYfstH7Za0FR1Awz3G"]],[16,-11,[0,"97sudGcIxGaYWuDKaoz7zx"],-10,-9,-8,-7,-6,-5]],[2,"05SGkUEUNLQ4l/NgwVXKob",null,null,null,-1,0]],[10,"jinbilandi",33554432,1,[-18,-19,-20,-21],[[1,-15,[0,"59oR95blNIyrY3JaP3R8wu"],[5,181,54]],[3,-16,[0,"f4Gm6OddlHyqsxVqAf5XkG"],6],[14,9,50,100,-17,[0,"1fmIw1X9xHuKz+/u0ij7+4"]]],[2,"4cVSNqXbxKAazQg4mLFLz1",null,null,null,1,0],[1,-234.5,593,0]],[11,"Sprite",33554432,1,[-25],[[1,-22,[0,"96fdcwuR9CN7c/xnGMq2Sy"],[5,750,1440]],[6,45,40,36,-23,[0,"5a6LheAFFNI53UR7Ib5VFE"]],[17,-24,[0,"23vNk/IEJPaoYb7A7qbCEw"]]],[2,"e1WGnIYT9DIK2g4fUadLsB",null,null,null,1,0]],[4,"+",33554432,2,[[1,-26,[0,"5eRBLiv75E/Zfit+GN8vif"],[5,62,62]],[3,-27,[0,"97ny04k0xBYZLjvQR49ygV"],2],[7,-28,[0,"28RkRmT9JAA5blCnR2iikW"],3]],[2,"9bWpZFjodBV7yvwTKZ3E75",null,null,null,1,0],[1,93.42,0,0]],[4,"yinoff",33554432,2,[[1,-29,[0,"81tPtc59VKc6ePCcF+BAk0"],[5,62,62]],[3,-30,[0,"9eNRD2FUlCWZD9vXNCaJIQ"],4],[7,-31,[0,"74fwzw6xxJjrGkV/7bv39e"],5]],[2,"c5UNFHu61OVJNeV7HD0yKm",null,null,null,1,0],[1,-75.322,-101.071,0]],[12,"点击屏幕开始游戏",33554432,3,[[1,-32,[0,"ddZzi8IA1AkZCP+/ZnZxfz"],[5,450,63]],[3,-33,[0,"f2SCBrjxZOG5EjfF1YGr+T"],0]],[2,"b3UUTT0mpE3YH/y9r0xxzS",null,null,null,1,0]],[5,"Label",33554432,1,[[[1,-34,[0,"c5bsPIEMVFIpqkS/1b/YOL"],[5,194.48,80]],-35,[15,17,200,680,80,-36,[0,"eeGVJdDZBLnofyLii4oZdS"]]],4,1,4],[2,"80NjI2pldPL7IywS2HoxOp",null,null,null,1,0],[1,0,480,0]],[4,"金币",33554432,2,[[1,-37,[0,"69cgiiN1hCWrt5D6Ofv695"],[5,70,63]],[3,-38,[0,"c15mFj6GZMxZvyh/LDFEGJ"],1]],[2,"17cjOa0mlB5bAzT2QBI4so",null,null,null,1,0],[1,-85.846,0,0]],[5,"Label",33554432,2,[[[1,-39,[0,"c4im7ZYW1Fg6TEXPyeAlHm"],[5,107.94,40]],-40],4,1],[2,"12VpGDAEFFkoQbjqM6Xdq8",null,null,null,1,0],[1,1.262,-5.05,0]],[18,"55555",40,false,9,[0,"a0bNZUZ8hI2q8tjA8arkpI"]],[19,"第8关",80,80,80,false,2,7,[0,"d8UcoRuZNNCbKNWyscU8Li"]]],0,[0,5,1,0,0,1,0,0,1,0,0,1,0,6,4,0,7,11,0,8,5,0,9,10,0,10,6,0,11,3,0,0,1,0,-1,3,0,-2,2,0,-3,7,0,0,2,0,0,2,0,0,2,0,-1,8,0,-2,4,0,-3,9,0,-4,5,0,0,3,0,0,3,0,0,3,0,-1,6,0,0,4,0,0,4,0,0,4,0,0,5,0,0,5,0,0,5,0,0,6,0,0,6,0,0,7,0,-2,11,0,0,7,0,0,8,0,0,8,0,0,9,0,-2,10,0,12,1,40],[0,0,0,0,0,0,0,10,11],[2,2,2,3,2,3,2,4,4],[6,7,0,0,1,1,8,2,2]],[[{"name":"jinbilandi","rect":{"x":0,"y":0,"width":181,"height":54},"offset":{"x":0,"y":0},"originalSize":{"width":181,"height":54},"rotated":false,"capInsets":[0,0,0,0],"vertices":{"rawPosition":[-90.5,-27,0,90.5,-27,0,-90.5,27,0,90.5,27,0],"indexes":[0,1,2,2,1,3],"uv":[0,54,181,54,0,0,181,0],"nuv":[0,0,1,0,0,1,1,1],"minPos":{"x":-90.5,"y":-27,"z":0},"maxPos":{"x":90.5,"y":27,"z":0}},"packable":true,"pixelsToUnit":100,"pivot":{"x":0.5,"y":0.5},"meshType":0}],[0],0,[0],[1],[9]],[[{"name":"yinoff","rect":{"x":0,"y":0,"width":62,"height":62},"offset":{"x":0,"y":0},"originalSize":{"width":62,"height":62},"rotated":false,"capInsets":[0,0,0,0],"vertices":{"rawPosition":[-31,-31,0,31,-31,0,-31,31,0,31,31,0],"indexes":[0,1,2,2,1,3],"uv":[0,62,62,62,0,0,62,0],"nuv":[0,0,1,0,0,1,1,1],"minPos":{"x":-31,"y":-31,"z":0},"maxPos":{"x":31,"y":31,"z":0}},"packable":true,"pixelsToUnit":100,"pivot":{"x":0.5,"y":0.5},"meshType":0}],[0],0,[0],[1],[10]]]]
